dbt/adapters/extrica/__init__.py
dbt/adapters/extrica/__version__.py
dbt/adapters/extrica/column.py
dbt/adapters/extrica/connections.py
dbt/adapters/extrica/impl.py
dbt/adapters/extrica/relation.py
dbt/adapters/extrica/token_handler.py
dbt/include/extrica/__init__.py
dbt/include/extrica/dbt_project.yml
dbt/include/extrica/sample_profiles.yml
dbt/include/extrica/macros/adapters.sql
dbt/include/extrica/macros/apply_grants.sql
dbt/include/extrica/macros/catalog.sql
dbt/include/extrica/macros/materializations/incremental.sql
dbt/include/extrica/macros/materializations/materialized_view.sql
dbt/include/extrica/macros/materializations/snapshot.sql
dbt/include/extrica/macros/materializations/table.sql
dbt/include/extrica/macros/materializations/view.sql
dbt/include/extrica/macros/materializations/seeds/helpers.sql
dbt/include/extrica/macros/utils/any_value.sql
dbt/include/extrica/macros/utils/array_append.sql
dbt/include/extrica/macros/utils/array_concat.sql
dbt/include/extrica/macros/utils/array_construct.sql
dbt/include/extrica/macros/utils/bool_or.sql
dbt/include/extrica/macros/utils/datatypes.sql
dbt/include/extrica/macros/utils/date_spine.sql
dbt/include/extrica/macros/utils/date_trunc.sql
dbt/include/extrica/macros/utils/dateadd.sql
dbt/include/extrica/macros/utils/datediff.sql
dbt/include/extrica/macros/utils/hash.sql
dbt/include/extrica/macros/utils/listagg.sql
dbt/include/extrica/macros/utils/right.sql
dbt/include/extrica/macros/utils/safe_cast.sql
dbt/include/extrica/macros/utils/split_part.sql
dbt/include/extrica/macros/utils/timestamps.sql
dbt_extrica-1.7.3.dist-info/METADATA
dbt_extrica-1.7.3.dist-info/WHEEL
dbt_extrica-1.7.3.dist-info/top_level.txt
dbt_extrica-1.7.3.dist-info/RECORD
