Metadata-Version: 2.1
Name: dbt-extrica
Version: 1.7.3
Summary: The trino adapter plugin for dbt (data build tool)
Home-page: https://github.com/starburstdata/dbt-trino
Author: Starburst Data
Author-email: info@starburstdata.com
License: Apache License 2.0
Platform: any
Classifier: Development Status :: 5 - Production/Stable
Classifier: License :: OSI Approved :: Apache Software License
Classifier: Operating System :: Microsoft :: Windows
Classifier: Operating System :: MacOS :: MacOS X
Classifier: Operating System :: POSIX :: Linux
Classifier: Programming Language :: Python :: 3.8
Classifier: Programming Language :: Python :: 3.9
Classifier: Programming Language :: Python :: 3.10
Classifier: Programming Language :: Python :: 3.11
Requires-Python: >=3.8
Requires-Dist: dbt-core ~=1.7.0
Requires-Dist: trino ~=0.326
